blue_yonder/__init__.py
blue_yonder/actor.py
blue_yonder/another.py
blue_yonder/utilities.py
blue_yonder/yonder.py
blue_yonder-0.1.34.dist-info/licenses/LICENSE
blue_yonder-0.1.34.dist-info/METADATA
blue_yonder-0.1.34.dist-info/WHEEL
blue_yonder-0.1.34.dist-info/top_level.txt
blue_yonder-0.1.34.dist-info/RECORD
