Metadata-Version: 2.4
Name: blue-yonder
Version: 0.1.34
Summary: Bluesky® Python API for humans.
Author-email: Alexander Fedotov <alex.fedotov@aol.com>
Project-URL: Homepage, https://github.com/alxfed/blue-yonder
Project-URL: Bug Tracker, https://github.com/alxfed/blue-yonder/issues
Keywords: bluesky,bsky,blue-yonder
Classifier: Programming Language :: Python :: 3
Classifier: License :: OSI Approved :: MIT License
Classifier: Operating System :: OS Independent
Requires-Python: >=3.10
License-File: LICENSE
Requires-Dist: requests>=2.32.3
Dynamic: license-file
